pip_dep_extractor/__init__.py
pip_dep_extractor-2025.9.101642.dist-info/licenses/LICENSE
pip_dep_extractor-2025.9.101642.dist-info/METADATA
pip_dep_extractor-2025.9.101642.dist-info/WHEEL
pip_dep_extractor-2025.9.101642.dist-info/top_level.txt
pip_dep_extractor-2025.9.101642.dist-info/RECORD
