Metadata-Version: 2.4
Name: pip_dep_extractor
Version: 2025.9.101642
Summary: Extracts 10 valid Python package names from an LLM response using llmatch.
Home-page: https://github.com/chigwell/pip_dep_extractor
Author: Eugene Evstafev
Author-email: hi@eugene.plus
License: MIT
Classifier: License :: OSI Approved :: MIT License
Classifier: Development Status :: 3 - Alpha
Classifier: Intended Audience :: Developers
Classifier: Programming Language :: Python :: 3
Classifier: Operating System :: OS Independent
Requires-Python: >=3.6
License-File: LICENSE
Dynamic: author
Dynamic: author-email
Dynamic: classifier
Dynamic: description
Dynamic: description-content-type
Dynamic: home-page
Dynamic: license
Dynamic: license-file
Dynamic: requires-python
Dynamic: summary
